[
 {
  "accept_payment": 0,
  "allow_comments": 1,
  "allow_delete": 1,
  "allow_edit": 1,
  "allow_incomplete": 0,
  "allow_multiple": 1,
  "allow_print": 0,
  "amount": 0.0,
  "amount_based_on_field": 0,
  "amount_field": null,
  "anonymous": 0,
  "apply_document_permissions": 0,
  "banner_image": null,
  "breadcrumbs": "[{\"label\":_(\"Issues\"), \"route\":\"issues\"}]",
  "button_label": null,
  "client_script": null,
  "condition": null,
  "currency": null,
  "custom_css": null,
  "doc_type": "Issue",
  "docstatus": 0,
  "doctype": "Web Form",
  "introduction_text": "",
  "is_standard": 1,
  "list_columns": [],
  "list_title": null,
  "login_required": 1,
  "max_attachment_size": 0,
  "meta_description": null,
  "meta_image": null,
  "meta_title": null,
  "modified": "2023-11-02 16:30:57.108214",
  "module": "Itam",
  "name": "issues",
  "payment_button_help": null,
  "payment_button_label": "Buy Now",
  "payment_gateway": null,
  "print_format": null,
  "published": 1,
  "route": "issues",
  "show_attachments": 1,
  "show_list": 1,
  "show_sidebar": 1,
  "success_message": "",
  "success_title": null,
  "success_url": "/issues",
  "title": "Issue",
  "web_form_fields": [
   {
    "allow_read_on_all_link_options": 0,
    "default": null,
    "depends_on": null,
    "description": null,
    "fieldname": "subject",
    "fieldtype": "Data",
    "hidden": 0,
    "label": "Subject",
    "mandatory_depends_on": null,
    "max_length": 0,
    "max_value": 0,
    "options": null,
    "parent": "issues",
    "parentfield": "web_form_fields",
    "parenttype": "Web Form",
    "read_only": 0,
    "read_only_depends_on": null,
    "reqd": 1,
    "show_in_filter": 0
   },
   {
    "allow_read_on_all_link_options": 0,
    "default": "Open",
    "depends_on": null,
    "description": null,
    "fieldname": "status",
    "fieldtype": "Select",
    "hidden": 0,
    "label": "Status",
    "mandatory_depends_on": null,
    "max_length": 0,
    "max_value": 0,
    "options": "Open\nReplied\nHold\nClosed",
    "parent": "issues",
    "parentfield": "web_form_fields",
    "parenttype": "Web Form",
    "read_only": 1,
    "read_only_depends_on": null,
    "reqd": 0,
    "show_in_filter": 1
   },
   {
    "allow_read_on_all_link_options": 0,
    "default": null,
    "depends_on": null,
    "description": null,
    "fieldname": "description",
    "fieldtype": "Text Editor",
    "hidden": 0,
    "label": "Description",
    "mandatory_depends_on": null,
    "max_length": 0,
    "max_value": 0,
    "options": null,
    "parent": "issues",
    "parentfield": "web_form_fields",
    "parenttype": "Web Form",
    "read_only": 0,
    "read_only_depends_on": null,
    "reqd": 0,
    "show_in_filter": 0
   },
   {
    "allow_read_on_all_link_options": 0,
    "default": "",
    "depends_on": null,
    "description": null,
    "fieldname": "attachment",
    "fieldtype": "Attach",
    "hidden": 0,
    "label": "Attachment",
    "mandatory_depends_on": null,
    "max_length": 0,
    "max_value": 0,
    "options": null,
    "parent": "issues",
    "parentfield": "web_form_fields",
    "parenttype": "Web Form",
    "read_only": 0,
    "read_only_depends_on": null,
    "reqd": 0,
    "show_in_filter": 0
   },
   {
    "allow_read_on_all_link_options": 0,
    "default": "\u0645\u0646\u062e\u0641\u0636",
    "depends_on": null,
    "description": null,
    "fieldname": "priority",
    "fieldtype": "Link",
    "hidden": 0,
    "label": "Priority",
    "mandatory_depends_on": null,
    "max_length": 0,
    "max_value": 0,
    "options": "Issue Priority",
    "parent": "issues",
    "parentfield": "web_form_fields",
    "parenttype": "Web Form",
    "read_only": 0,
    "read_only_depends_on": null,
    "reqd": 1,
    "show_in_filter": 0
   },
   {
    "allow_read_on_all_link_options": 0,
    "default": "1",
    "depends_on": null,
    "description": null,
    "fieldname": "via_customer_portal",
    "fieldtype": "Check",
    "hidden": 1,
    "label": "Via Customer Portal",
    "mandatory_depends_on": null,
    "max_length": 0,
    "max_value": 0,
    "options": null,
    "parent": "issues",
    "parentfield": "web_form_fields",
    "parenttype": "Web Form",
    "read_only": 1,
    "read_only_depends_on": null,
    "reqd": 0,
    "show_in_filter": 0
   }
  ],
  "website_sidebar": "Employee Sidebar"
 },
 {
  "accept_payment": 0,
  "allow_comments": 1,
  "allow_delete": 1,
  "allow_edit": 1,
  "allow_incomplete": 0,
  "allow_multiple": 1,
  "allow_print": 0,
  "amount": 0.0,
  "amount_based_on_field": 0,
  "amount_field": null,
  "anonymous": 0,
  "apply_document_permissions": 0,
  "banner_image": null,
  "breadcrumbs": "[{\"label\":_(\"Material Request\"), \"route\":\"material-request\"}]",
  "button_label": "Save",
  "client_script": null,
  "condition": null,
  "currency": "SAR",
  "custom_css": null,
  "doc_type": "Material Request",
  "docstatus": 0,
  "doctype": "Web Form",
  "introduction_text": null,
  "is_standard": 1,
  "list_columns": [
   {
    "fieldname": "customer",
    "fieldtype": "Link",
    "label": "Customer",
    "parent": "material-request",
    "parentfield": "list_columns",
    "parenttype": "Web Form"
   },
   {
    "fieldname": "naming_series",
    "fieldtype": "Select",
    "label": "Series",
    "parent": "material-request",
    "parentfield": "list_columns",
    "parenttype": "Web Form"
   },
   {
    "fieldname": "title",
    "fieldtype": "Data",
    "label": "Title",
    "parent": "material-request",
    "parentfield": "list_columns",
    "parenttype": "Web Form"
   }
  ],
  "list_title": null,
  "login_required": 1,
  "max_attachment_size": 0,
  "meta_description": null,
  "meta_image": null,
  "meta_title": null,
  "modified": "2023-11-02 17:45:38.214044",
  "module": "Itam",
  "name": "material-request",
  "payment_button_help": null,
  "payment_button_label": "Buy Now",
  "payment_gateway": null,
  "print_format": null,
  "published": 1,
  "route": "material-request",
  "show_attachments": 0,
  "show_list": 1,
  "show_sidebar": 1,
  "success_message": null,
  "success_title": null,
  "success_url": "/material-request",
  "title": "Material Request",
  "web_form_fields": [
   {
    "allow_read_on_all_link_options": 0,
    "default": "MAT-MR-.YYYY.-",
    "depends_on": null,
    "description": null,
    "fieldname": "naming_series",
    "fieldtype": "Select",
    "hidden": 1,
    "label": "Series",
    "mandatory_depends_on": null,
    "max_length": 0,
    "max_value": 0,
    "options": "MAT-MR-.YYYY.-",
    "parent": "material-request",
    "parentfield": "web_form_fields",
    "parenttype": "Web Form",
    "read_only": 0,
    "read_only_depends_on": null,
    "reqd": 1,
    "show_in_filter": 0
   },
   {
    "allow_read_on_all_link_options": 0,
    "default": "Material Issue",
    "depends_on": null,
    "description": null,
    "fieldname": "material_request_type",
    "fieldtype": "Select",
    "hidden": 0,
    "label": "Purpose",
    "mandatory_depends_on": null,
    "max_length": 0,
    "max_value": 0,
    "options": "Material Issue",
    "parent": "material-request",
    "parentfield": "web_form_fields",
    "parenttype": "Web Form",
    "read_only": 0,
    "read_only_depends_on": null,
    "reqd": 1,
    "show_in_filter": 0
   },
   {
    "allow_read_on_all_link_options": 0,
    "default": null,
    "depends_on": "eval:doc.material_request_type==\"Customer Provided\"",
    "description": null,
    "fieldname": "customer",
    "fieldtype": "Link",
    "hidden": 0,
    "label": "Customer",
    "mandatory_depends_on": null,
    "max_length": 0,
    "max_value": 0,
    "options": "Customer",
    "parent": "material-request",
    "parentfield": "web_form_fields",
    "parenttype": "Web Form",
    "read_only": 0,
    "read_only_depends_on": null,
    "reqd": 0,
    "show_in_filter": 0
   },
   {
    "allow_read_on_all_link_options": 0,
    "default": "IT Systematic",
    "depends_on": null,
    "description": null,
    "fieldname": "company",
    "fieldtype": "Link",
    "hidden": 1,
    "label": "Company",
    "mandatory_depends_on": null,
    "max_length": 0,
    "max_value": 0,
    "options": "Company",
    "parent": "material-request",
    "parentfield": "web_form_fields",
    "parenttype": "Web Form",
    "read_only": 0,
    "read_only_depends_on": null,
    "reqd": 1,
    "show_in_filter": 0
   },
   {
    "allow_read_on_all_link_options": 0,
    "default": "Today",
    "depends_on": null,
    "description": null,
    "fieldname": "transaction_date",
    "fieldtype": "Date",
    "hidden": 0,
    "label": "Transaction Date",
    "mandatory_depends_on": null,
    "max_length": 0,
    "max_value": 0,
    "options": null,
    "parent": "material-request",
    "parentfield": "web_form_fields",
    "parenttype": "Web Form",
    "read_only": 0,
    "read_only_depends_on": null,
    "reqd": 1,
    "show_in_filter": 0
   },
   {
    "allow_read_on_all_link_options": 0,
    "default": null,
    "depends_on": null,
    "description": null,
    "fieldname": "schedule_date",
    "fieldtype": "Date",
    "hidden": 0,
    "label": "Required By",
    "mandatory_depends_on": null,
    "max_length": 0,
    "max_value": 0,
    "options": null,
    "parent": "material-request",
    "parentfield": "web_form_fields",
    "parenttype": "Web Form",
    "read_only": 0,
    "read_only_depends_on": null,
    "reqd": 0,
    "show_in_filter": 0
   },
   {
    "allow_read_on_all_link_options": 0,
    "default": null,
    "depends_on": "eval:doc.material_request_type == 'Material Transfer'",
    "description": null,
    "fieldname": "set_from_warehouse",
    "fieldtype": "Link",
    "hidden": 0,
    "label": "Set Source Warehouse",
    "mandatory_depends_on": null,
    "max_length": 0,
    "max_value": 0,
    "options": "Warehouse",
    "parent": "material-request",
    "parentfield": "web_form_fields",
    "parenttype": "Web Form",
    "read_only": 0,
    "read_only_depends_on": null,
    "reqd": 0,
    "show_in_filter": 0
   },
   {
    "allow_read_on_all_link_options": 0,
    "default": null,
    "depends_on": null,
    "description": null,
    "fieldname": "items",
    "fieldtype": "Table",
    "hidden": 0,
    "label": "Items",
    "mandatory_depends_on": null,
    "max_length": 0,
    "max_value": 0,
    "options": "Material Request Item",
    "parent": "material-request",
    "parentfield": "web_form_fields",
    "parenttype": "Web Form",
    "read_only": 0,
    "read_only_depends_on": null,
    "reqd": 1,
    "show_in_filter": 0
   },
   {
    "allow_read_on_all_link_options": 0,
    "default": null,
    "depends_on": null,
    "description": null,
    "fieldname": "tc_name",
    "fieldtype": "Link",
    "hidden": 1,
    "label": "Terms",
    "mandatory_depends_on": null,
    "max_length": 0,
    "max_value": 0,
    "options": "Terms and Conditions",
    "parent": "material-request",
    "parentfield": "web_form_fields",
    "parenttype": "Web Form",
    "read_only": 0,
    "read_only_depends_on": null,
    "reqd": 0,
    "show_in_filter": 0
   },
   {
    "allow_read_on_all_link_options": 0,
    "default": null,
    "depends_on": null,
    "description": null,
    "fieldname": "terms",
    "fieldtype": "Text Editor",
    "hidden": 1,
    "label": "Terms and Conditions Content",
    "mandatory_depends_on": null,
    "max_length": 0,
    "max_value": 0,
    "options": null,
    "parent": "material-request",
    "parentfield": "web_form_fields",
    "parenttype": "Web Form",
    "read_only": 0,
    "read_only_depends_on": null,
    "reqd": 0,
    "show_in_filter": 0
   },
   {
    "allow_read_on_all_link_options": 0,
    "default": null,
    "depends_on": null,
    "description": null,
    "fieldname": "status",
    "fieldtype": "Select",
    "hidden": 0,
    "label": "Status",
    "mandatory_depends_on": null,
    "max_length": 0,
    "max_value": 0,
    "options": "\nDraft\nSubmitted\nStopped\nCancelled\nPending\nPartially Ordered\nPartially Received\nOrdered\nIssued\nTransferred\nReceived",
    "parent": "material-request",
    "parentfield": "web_form_fields",
    "parenttype": "Web Form",
    "read_only": 1,
    "read_only_depends_on": null,
    "reqd": 0,
    "show_in_filter": 0
   },
   {
    "allow_read_on_all_link_options": 0,
    "default": null,
    "depends_on": "eval:doc.add_to_transit == 1",
    "description": null,
    "fieldname": "transfer_status",
    "fieldtype": "Select",
    "hidden": 1,
    "label": "Transfer Status",
    "mandatory_depends_on": null,
    "max_length": 0,
    "max_value": 0,
    "options": "\nNot Started\nIn Transit\nCompleted",
    "parent": "material-request",
    "parentfield": "web_form_fields",
    "parenttype": "Web Form",
    "read_only": 1,
    "read_only_depends_on": null,
    "reqd": 0,
    "show_in_filter": 0
   },
   {
    "allow_read_on_all_link_options": 0,
    "default": null,
    "depends_on": "",
    "description": null,
    "fieldname": "letter_head",
    "fieldtype": "Link",
    "hidden": 1,
    "label": "Letter Head",
    "mandatory_depends_on": null,
    "max_length": 0,
    "max_value": 0,
    "options": "Letter Head",
    "parent": "material-request",
    "parentfield": "web_form_fields",
    "parenttype": "Web Form",
    "read_only": 0,
    "read_only_depends_on": null,
    "reqd": 0,
    "show_in_filter": 0
   },
   {
    "allow_read_on_all_link_options": 0,
    "default": null,
    "depends_on": null,
    "description": null,
    "fieldname": "select_print_heading",
    "fieldtype": "Link",
    "hidden": 1,
    "label": "Print Heading",
    "mandatory_depends_on": null,
    "max_length": 0,
    "max_value": 0,
    "options": "Print Heading",
    "parent": "material-request",
    "parentfield": "web_form_fields",
    "parenttype": "Web Form",
    "read_only": 0,
    "read_only_depends_on": null,
    "reqd": 0,
    "show_in_filter": 0
   },
   {
    "allow_read_on_all_link_options": 0,
    "default": null,
    "depends_on": null,
    "description": null,
    "fieldname": "job_card",
    "fieldtype": "Link",
    "hidden": 1,
    "label": "Job Card",
    "mandatory_depends_on": null,
    "max_length": 0,
    "max_value": 0,
    "options": "Job Card",
    "parent": "material-request",
    "parentfield": "web_form_fields",
    "parenttype": "Web Form",
    "read_only": 1,
    "read_only_depends_on": null,
    "reqd": 0,
    "show_in_filter": 0
   },
   {
    "allow_read_on_all_link_options": 0,
    "default": null,
    "depends_on": null,
    "description": null,
    "fieldname": "work_order",
    "fieldtype": "Link",
    "hidden": 1,
    "label": "Work Order",
    "mandatory_depends_on": null,
    "max_length": 0,
    "max_value": 0,
    "options": "Work Order",
    "parent": "material-request",
    "parentfield": "web_form_fields",
    "parenttype": "Web Form",
    "read_only": 1,
    "read_only_depends_on": null,
    "reqd": 0,
    "show_in_filter": 0
   }
  ],
  "website_sidebar": "Employee Sidebar"
 },
 {
  "accept_payment": 0,
  "allow_comments": 0,
  "allow_delete": 0,
  "allow_edit": 0,
  "allow_incomplete": 0,
  "allow_multiple": 1,
  "allow_print": 0,
  "amount": 0.0,
  "amount_based_on_field": 0,
  "amount_field": null,
  "anonymous": 0,
  "apply_document_permissions": 0,
  "banner_image": null,
  "breadcrumbs": "[{\"label\": _(\"Issues\"), \"route\":\"/issues-web\"}]",
  "button_label": "Save",
  "client_script": null,
  "condition": null,
  "currency": "SAR",
  "custom_css": null,
  "doc_type": "Issue",
  "docstatus": 0,
  "doctype": "Web Form",
  "introduction_text": null,
  "is_standard": 0,
  "list_columns": [],
  "list_title": null,
  "login_required": 1,
  "max_attachment_size": 0,
  "meta_description": null,
  "meta_image": null,
  "meta_title": null,
  "modified": "2023-11-07 15:27:38.754201",
  "module": "Itam",
  "name": "issues-web",
  "payment_button_help": null,
  "payment_button_label": "Buy Now",
  "payment_gateway": null,
  "print_format": null,
  "published": 1,
  "route": "issues-web",
  "show_attachments": 1,
  "show_list": 1,
  "show_sidebar": 1,
  "success_message": null,
  "success_title": null,
  "success_url": null,
  "title": "Issues",
  "web_form_fields": [
   {
    "allow_read_on_all_link_options": 0,
    "default": null,
    "depends_on": null,
    "description": null,
    "fieldname": "subject",
    "fieldtype": "Data",
    "hidden": 0,
    "label": "Subject",
    "mandatory_depends_on": null,
    "max_length": 0,
    "max_value": 0,
    "options": null,
    "parent": "issues-web",
    "parentfield": "web_form_fields",
    "parenttype": "Web Form",
    "read_only": 0,
    "read_only_depends_on": null,
    "reqd": 1,
    "show_in_filter": 0
   },
   {
    "allow_read_on_all_link_options": 0,
    "default": "Open",
    "depends_on": null,
    "description": null,
    "fieldname": "status",
    "fieldtype": "Select",
    "hidden": 0,
    "label": "Status",
    "mandatory_depends_on": null,
    "max_length": 0,
    "max_value": 0,
    "options": "Open\nReplied\nOn Hold\nResolved\nClosed",
    "parent": "issues-web",
    "parentfield": "web_form_fields",
    "parenttype": "Web Form",
    "read_only": 0,
    "read_only_depends_on": null,
    "reqd": 0,
    "show_in_filter": 0
   },
   {
    "allow_read_on_all_link_options": 0,
    "default": null,
    "depends_on": null,
    "description": null,
    "fieldname": "description",
    "fieldtype": "Text Editor",
    "hidden": 0,
    "label": "Description",
    "mandatory_depends_on": null,
    "max_length": 0,
    "max_value": 0,
    "options": null,
    "parent": "issues-web",
    "parentfield": "web_form_fields",
    "parenttype": "Web Form",
    "read_only": 0,
    "read_only_depends_on": null,
    "reqd": 0,
    "show_in_filter": 0
   },
   {
    "allow_read_on_all_link_options": 0,
    "default": null,
    "depends_on": null,
    "description": null,
    "fieldname": "attachment",
    "fieldtype": "Attach",
    "hidden": 0,
    "label": "Attachment",
    "mandatory_depends_on": null,
    "max_length": 0,
    "max_value": 0,
    "options": null,
    "parent": "issues-web",
    "parentfield": "web_form_fields",
    "parenttype": "Web Form",
    "read_only": 0,
    "read_only_depends_on": null,
    "reqd": 0,
    "show_in_filter": 0
   },
   {
    "allow_read_on_all_link_options": 0,
    "default": "Mid-Level",
    "depends_on": null,
    "description": null,
    "fieldname": "priority",
    "fieldtype": "Link",
    "hidden": 0,
    "label": "Priority",
    "mandatory_depends_on": null,
    "max_length": 0,
    "max_value": 0,
    "options": "Issue Priority",
    "parent": "issues-web",
    "parentfield": "web_form_fields",
    "parenttype": "Web Form",
    "read_only": 0,
    "read_only_depends_on": null,
    "reqd": 0,
    "show_in_filter": 0
   }
  ],
  "website_sidebar": "Home Page Sidebar"
 },
 {
  "accept_payment": 0,
  "allow_comments": 1,
  "allow_delete": 0,
  "allow_edit": 0,
  "allow_incomplete": 0,
  "allow_multiple": 1,
  "allow_print": 0,
  "amount": 0.0,
  "amount_based_on_field": 0,
  "amount_field": null,
  "anonymous": 0,
  "apply_document_permissions": 0,
  "banner_image": null,
  "breadcrumbs": "[{\"label\": _(\"Requests\"), \"route\":\"material-request-web\"}]",
  "button_label": "Save",
  "client_script": "let me = frappe.web_form;\r\nlet field = me.get_field('items').df.fields[3];\r\nconsole.log(field)",
  "condition": null,
  "currency": "SAR",
  "custom_css": null,
  "doc_type": "Material Request",
  "docstatus": 0,
  "doctype": "Web Form",
  "introduction_text": null,
  "is_standard": 0,
  "list_columns": [],
  "list_title": "",
  "login_required": 1,
  "max_attachment_size": 0,
  "meta_description": null,
  "meta_image": null,
  "meta_title": null,
  "modified": "2023-11-09 11:04:24.144345",
  "module": "Stock",
  "name": "material-request-web",
  "payment_button_help": null,
  "payment_button_label": "Buy Now",
  "payment_gateway": null,
  "print_format": null,
  "published": 1,
  "route": "material-request-web",
  "show_attachments": 0,
  "show_list": 1,
  "show_sidebar": 1,
  "success_message": null,
  "success_title": null,
  "success_url": "",
  "title": "Material-Requests",
  "web_form_fields": [
   {
    "allow_read_on_all_link_options": 0,
    "default": "MAT-MR-.YYYY.-",
    "depends_on": null,
    "description": null,
    "fieldname": "naming_series",
    "fieldtype": "Select",
    "hidden": 1,
    "label": "Series",
    "mandatory_depends_on": null,
    "max_length": 0,
    "max_value": 0,
    "options": "MAT-MR-.YYYY.-",
    "parent": "material-request-web",
    "parentfield": "web_form_fields",
    "parenttype": "Web Form",
    "read_only": 0,
    "read_only_depends_on": null,
    "reqd": 1,
    "show_in_filter": 0
   },
   {
    "allow_read_on_all_link_options": 0,
    "default": "Material Issue",
    "depends_on": null,
    "description": null,
    "fieldname": "material_request_type",
    "fieldtype": "Select",
    "hidden": 0,
    "label": "Purpose",
    "mandatory_depends_on": null,
    "max_length": 0,
    "max_value": 0,
    "options": "Material Issue",
    "parent": "material-request-web",
    "parentfield": "web_form_fields",
    "parenttype": "Web Form",
    "read_only": 0,
    "read_only_depends_on": null,
    "reqd": 1,
    "show_in_filter": 0
   },
   {
    "allow_read_on_all_link_options": 0,
    "default": null,
    "depends_on": "eval:doc.material_request_type==\"Customer Provided\"",
    "description": null,
    "fieldname": "customer",
    "fieldtype": "Link",
    "hidden": 0,
    "label": "Customer",
    "mandatory_depends_on": null,
    "max_length": 0,
    "max_value": 0,
    "options": "Customer",
    "parent": "material-request-web",
    "parentfield": "web_form_fields",
    "parenttype": "Web Form",
    "read_only": 0,
    "read_only_depends_on": null,
    "reqd": 0,
    "show_in_filter": 0
   },
   {
    "allow_read_on_all_link_options": 0,
    "default": "IT Systematic",
    "depends_on": null,
    "description": null,
    "fieldname": "company",
    "fieldtype": "Link",
    "hidden": 1,
    "label": "Company",
    "mandatory_depends_on": null,
    "max_length": 0,
    "max_value": 0,
    "options": "Company",
    "parent": "material-request-web",
    "parentfield": "web_form_fields",
    "parenttype": "Web Form",
    "read_only": 0,
    "read_only_depends_on": null,
    "reqd": 1,
    "show_in_filter": 0
   },
   {
    "allow_read_on_all_link_options": 0,
    "default": "Today",
    "depends_on": null,
    "description": null,
    "fieldname": "transaction_date",
    "fieldtype": "Date",
    "hidden": 0,
    "label": "Transaction Date",
    "mandatory_depends_on": null,
    "max_length": 0,
    "max_value": 0,
    "options": null,
    "parent": "material-request-web",
    "parentfield": "web_form_fields",
    "parenttype": "Web Form",
    "read_only": 0,
    "read_only_depends_on": null,
    "reqd": 1,
    "show_in_filter": 0
   },
   {
    "allow_read_on_all_link_options": 0,
    "default": null,
    "depends_on": null,
    "description": null,
    "fieldname": "schedule_date",
    "fieldtype": "Date",
    "hidden": 0,
    "label": "Required By",
    "mandatory_depends_on": null,
    "max_length": 0,
    "max_value": 0,
    "options": null,
    "parent": "material-request-web",
    "parentfield": "web_form_fields",
    "parenttype": "Web Form",
    "read_only": 0,
    "read_only_depends_on": null,
    "reqd": 0,
    "show_in_filter": 0
   },
   {
    "allow_read_on_all_link_options": 0,
    "default": null,
    "depends_on": "eval:doc.material_request_type == 'Material Transfer'",
    "description": null,
    "fieldname": "set_from_warehouse",
    "fieldtype": "Link",
    "hidden": 0,
    "label": "Set Source Warehouse",
    "mandatory_depends_on": null,
    "max_length": 0,
    "max_value": 0,
    "options": "Warehouse",
    "parent": "material-request-web",
    "parentfield": "web_form_fields",
    "parenttype": "Web Form",
    "read_only": 0,
    "read_only_depends_on": null,
    "reqd": 0,
    "show_in_filter": 0
   },
   {
    "allow_read_on_all_link_options": 0,
    "default": null,
    "depends_on": null,
    "description": null,
    "fieldname": "items",
    "fieldtype": "Table",
    "hidden": 0,
    "label": "Items",
    "mandatory_depends_on": null,
    "max_length": 0,
    "max_value": 0,
    "options": "Material Request Item",
    "parent": "material-request-web",
    "parentfield": "web_form_fields",
    "parenttype": "Web Form",
    "read_only": 0,
    "read_only_depends_on": null,
    "reqd": 1,
    "show_in_filter": 0
   },
   {
    "allow_read_on_all_link_options": 0,
    "default": null,
    "depends_on": null,
    "description": null,
    "fieldname": "tc_name",
    "fieldtype": "Link",
    "hidden": 1,
    "label": "Terms",
    "mandatory_depends_on": null,
    "max_length": 0,
    "max_value": 0,
    "options": "Terms and Conditions",
    "parent": "material-request-web",
    "parentfield": "web_form_fields",
    "parenttype": "Web Form",
    "read_only": 0,
    "read_only_depends_on": null,
    "reqd": 0,
    "show_in_filter": 0
   },
   {
    "allow_read_on_all_link_options": 0,
    "default": null,
    "depends_on": null,
    "description": null,
    "fieldname": "terms",
    "fieldtype": "Text Editor",
    "hidden": 1,
    "label": "Terms and Conditions Content",
    "mandatory_depends_on": null,
    "max_length": 0,
    "max_value": 0,
    "options": null,
    "parent": "material-request-web",
    "parentfield": "web_form_fields",
    "parenttype": "Web Form",
    "read_only": 0,
    "read_only_depends_on": null,
    "reqd": 0,
    "show_in_filter": 0
   },
   {
    "allow_read_on_all_link_options": 0,
    "default": "New",
    "depends_on": null,
    "description": null,
    "fieldname": "custom_request_type",
    "fieldtype": "Select",
    "hidden": 0,
    "label": "Request Type",
    "mandatory_depends_on": null,
    "max_length": 0,
    "max_value": 0,
    "options": "New\nUpdate",
    "parent": "material-request-web",
    "parentfield": "web_form_fields",
    "parenttype": "Web Form",
    "read_only": 0,
    "read_only_depends_on": null,
    "reqd": 0,
    "show_in_filter": 0
   },
   {
    "allow_read_on_all_link_options": 0,
    "default": null,
    "depends_on": "eval:doc.add_to_transit == 1",
    "description": null,
    "fieldname": "transfer_status",
    "fieldtype": "Select",
    "hidden": 1,
    "label": "Transfer Status",
    "mandatory_depends_on": null,
    "max_length": 0,
    "max_value": 0,
    "options": "\nNot Started\nIn Transit\nCompleted",
    "parent": "material-request-web",
    "parentfield": "web_form_fields",
    "parenttype": "Web Form",
    "read_only": 1,
    "read_only_depends_on": null,
    "reqd": 0,
    "show_in_filter": 0
   },
   {
    "allow_read_on_all_link_options": 0,
    "default": null,
    "depends_on": null,
    "description": null,
    "fieldname": "letter_head",
    "fieldtype": "Link",
    "hidden": 1,
    "label": "Letter Head",
    "mandatory_depends_on": null,
    "max_length": 0,
    "max_value": 0,
    "options": "Letter Head",
    "parent": "material-request-web",
    "parentfield": "web_form_fields",
    "parenttype": "Web Form",
    "read_only": 0,
    "read_only_depends_on": null,
    "reqd": 0,
    "show_in_filter": 0
   },
   {
    "allow_read_on_all_link_options": 0,
    "default": null,
    "depends_on": null,
    "description": null,
    "fieldname": "select_print_heading",
    "fieldtype": "Link",
    "hidden": 1,
    "label": "Print Heading",
    "mandatory_depends_on": null,
    "max_length": 0,
    "max_value": 0,
    "options": "Print Heading",
    "parent": "material-request-web",
    "parentfield": "web_form_fields",
    "parenttype": "Web Form",
    "read_only": 0,
    "read_only_depends_on": null,
    "reqd": 0,
    "show_in_filter": 0
   },
   {
    "allow_read_on_all_link_options": 0,
    "default": null,
    "depends_on": null,
    "description": null,
    "fieldname": "job_card",
    "fieldtype": "Link",
    "hidden": 1,
    "label": "Job Card",
    "mandatory_depends_on": null,
    "max_length": 0,
    "max_value": 0,
    "options": "Job Card",
    "parent": "material-request-web",
    "parentfield": "web_form_fields",
    "parenttype": "Web Form",
    "read_only": 1,
    "read_only_depends_on": null,
    "reqd": 0,
    "show_in_filter": 0
   },
   {
    "allow_read_on_all_link_options": 0,
    "default": null,
    "depends_on": null,
    "description": null,
    "fieldname": "work_order",
    "fieldtype": "Link",
    "hidden": 1,
    "label": "Work Order",
    "mandatory_depends_on": null,
    "max_length": 0,
    "max_value": 0,
    "options": "Work Order",
    "parent": "material-request-web",
    "parentfield": "web_form_fields",
    "parenttype": "Web Form",
    "read_only": 1,
    "read_only_depends_on": null,
    "reqd": 0,
    "show_in_filter": 0
   }
  ],
  "website_sidebar": "Home Page Sidebar"
 }
]